airflow_aws_cost_explorer/__init__.py
airflow_aws_cost_explorer/plugin.py
airflow_aws_cost_explorer/operators/__init__.py
airflow_aws_cost_explorer/operators/aws_bucket_size.py
airflow_aws_cost_explorer/operators/aws_cost_explorer.py
airflow_aws_cost_explorer/operators/commons.py
airflow_aws_cost_explorer-1.3.0.dist-info/LICENSE
airflow_aws_cost_explorer-1.3.0.dist-info/METADATA
airflow_aws_cost_explorer-1.3.0.dist-info/WHEEL
airflow_aws_cost_explorer-1.3.0.dist-info/entry_points.txt
airflow_aws_cost_explorer-1.3.0.dist-info/top_level.txt
airflow_aws_cost_explorer-1.3.0.dist-info/RECORD
