Metadata-Version: 2.1
Name: airflow-aws-cost-explorer
Version: 1.3.0
Summary: Apache Airflow Operator exporting AWS Cost Explorer data to local file or S3
Home-page: https://github.com/andreax79/airflow-aws-cost-explorer
Author: Andrea Bonomi
Author-email: andrea.bonomi@gmail.com
License: Apache License, Version 2.0
Platform: UNKNOWN
Classifier: Operating System :: OS Independent
Classifier: Programming Language :: Python
Classifier: Topic :: Software Development :: Libraries :: Python Modules
Classifier: Programming Language :: Python :: 3
Classifier: Programming Language :: Python :: 3.3
Classifier: Programming Language :: Python :: 3.4
Classifier: Programming Language :: Python :: 3.5
Classifier: Programming Language :: Python :: 3.6
Classifier: Programming Language :: Python :: 3.7
Classifier: Programming Language :: Python :: 3.8
Requires-Dist: apache-airflow
